trade_trails/__init__.py
trade_trails-0.0.2.dist-info/METADATA
trade_trails-0.0.2.dist-info/WHEEL
trade_trails-0.0.2.dist-info/top_level.txt
trade_trails-0.0.2.dist-info/RECORD
