Metadata-Version: 2.1
Name: trade-trails
Version: 0.0.2
Summary: This Library is only For Trade Trails Company
Author: Krishna Gupta
Author-email: kg158454@gmail.com
Keywords: python,trade_trails,trade_trails library,pip install trade_trails,Trade_trails pip install
Classifier: Development Status :: 1 - Planning
Classifier: Intended Audience :: Developers
Classifier: Programming Language :: Python :: 3
Classifier: Operating System :: Unix
Classifier: Operating System :: MacOS :: MacOS X
Classifier: Operating System :: Microsoft :: Windows
Requires-Dist: pandas
Requires-Dist: colorama
Requires-Dist: datetime
